ML/Run.py
ML/Utils.py
ML/__init__.py
ML/Agents/AC2Agent.py
ML/Agents/__init__.py
ML/Agents/Blocks/Actors.py
ML/Agents/Blocks/Augmentations.py
ML/Agents/Blocks/Creator.py
ML/Agents/Blocks/Critics.py
ML/Agents/Blocks/Encoders.py
ML/Agents/Blocks/Architectures/Distributions.py
ML/Agents/Blocks/Architectures/Ensemble.py
ML/Agents/Blocks/Architectures/MLP.py
ML/Agents/Blocks/Architectures/MultiHeadAttention.py
ML/Agents/Blocks/Architectures/Perceiver.py
ML/Agents/Blocks/Architectures/RN.py
ML/Agents/Blocks/Architectures/Residual.py
ML/Agents/Blocks/Architectures/Transformer.py
ML/Agents/Blocks/Architectures/__init__.py
ML/Agents/Blocks/Architectures/Vision/CNN.py
ML/Agents/Blocks/Architectures/Vision/CoAtNet.py
ML/Agents/Blocks/Architectures/Vision/ConvMixer.py
ML/Agents/Blocks/Architectures/Vision/ConvNeXt.py
ML/Agents/Blocks/Architectures/Vision/DCGAN.py
ML/Agents/Blocks/Architectures/Vision/ResNet.py
ML/Agents/Blocks/Architectures/Vision/TIMM.py
ML/Agents/Blocks/Architectures/Vision/ViT.py
ML/Agents/Blocks/Architectures/Vision/__init__.py
ML/Agents/Blocks/Architectures/Vision/FoundationModels/GroundingDINO.py
ML/Agents/Examples/DQN.py
ML/Agents/Examples/DrQV2.py
ML/Agents/Examples/DuelingDQN.py
ML/Agents/Examples/HardDQN.py
ML/Agents/Examples/Random.py
ML/Agents/Losses/PolicyLearning.py
ML/Agents/Losses/QLearning.py
ML/Agents/Losses/SelfSupervisedLearning.py
ML/Benchmarking/Logger.py
ML/Benchmarking/Plot.py
ML/Benchmarking/Vlogger.py
ML/Benchmarking/Logs/Exp/Agent/DMC/cheetah_run_1_Command_Line_Args.yaml
ML/Benchmarking/Logs/Exp/Agent/classify/MNIST_1_Command_Line_Args.yaml
ML/Hyperparams/args.yaml
ML/Hyperparams/task/RL.yaml
ML/Hyperparams/task/atari.yaml
ML/Hyperparams/task/classify.yaml
ML/Hyperparams/task/dmc.yaml
ML/Hyperparams/task/generate.yaml
ML/Hyperparams/task/mario.yaml
ML/Hyperparams/task/regression.yaml
ML/Hyperparams/task/supervised.yaml
ML/Hyperparams/task/atari/adventure.yaml
ML/Hyperparams/task/atari/airraid.yaml
ML/Hyperparams/task/atari/alien.yaml
UnifiedML-1.0.6.dist-info/METADATA
UnifiedML-1.0.6.dist-info/WHEEL
UnifiedML-1.0.6.dist-info/entry_points.txt
UnifiedML-1.0.6.dist-info/top_level.txt
UnifiedML-1.0.6.dist-info/RECORD
