Metadata-Version: 2.1
Name: UnifiedML
Version: 1.0.6
Summary: Unified library for intelligence training.
Home-page: https://github.com/agi-init/UnifiedML
Author: Sam Lerman
Author-email: agi.init@gmail.com
Project-URL: Bug Tracker, https://github.com/agi-init/UnifiedML/issues
Keywords: artificial intelligence,machine learning,deep learning,reinforcement learning,image classification
Classifier: Programming Language :: Python
Classifier: License :: OSI Approved :: MIT License
Classifier: Operating System :: OS Independent
Requires-Python: >=3.10.8
Requires-Dist: torch (==2.0.1)
Requires-Dist: torchvision (==0.15.2)
Requires-Dist: torchaudio (==2.0.2)
Requires-Dist: pandas (==1.5.3)
Requires-Dist: autorom[accept-rom-license] (==0.6.1)
Requires-Dist: ale-py (==0.8.1)
Requires-Dist: gym-super-mario-bros (==7.4)
Requires-Dist: dm-control (==1.0.16)
Requires-Dist: PyOpenGL-accelerate (==3.1.7)
Requires-Dist: termcolor (==1.1)
Requires-Dist: seaborn (==0.11.2)
Requires-Dist: wandb (==0.12.17)
Requires-Dist: imageio (==2.22)
Requires-Dist: imageio-ffmpeg (==0.4.7)
Requires-Dist: einops (==0.4.1)
Requires-Dist: dill (==0.3.7)
Requires-Dist: bleak (==0.19.5)
Requires-Dist: minihydra-leviathan (==1.0.1)
